Workbook

Sheet Assumptions
A1: Scenarios | B1: Base
A2: Core Operating Assumptions | B2: 2026 | C2: 2027 | D2: 2028 | E2: 2029 | F2: 2030 | G2: 2031 | H2: 2032 | I2: 2033 | J2: 2034 | K2: 2035
A3: Revenue Growth by Year | B3: =INDEX(Scenarios!B3:B5, MATCH($B$1, Scenarios!A3:A5, 0)) -> 0.09 | C3: =B3-0.01 -> 0.08 | D3: =C3-0.01 -> 0.07 | E3: =D3-0.02 -> 0.05 | F3: =E3-0.02 -> 0.03 | G3: =F3 -> 0.03 | H3: =G3 -> 0.03 | I3: =H3-0.01 -> 0.02 | J3: =I3 -> 0.02 | K3: =J3 -> 0.02
A4: Target EBITDA Margin by Year | B4: =INDEX(Scenarios!C3:C5, MATCH($B$1, Scenarios!A3:A5, 0)) -> 0.21 | C4: =B4+0.01 -> 0.22 | D4: =C4+0.01 -> 0.23 | E4: =D4 -> 0.23 | F4: =E4 -> 0.23 | G4: =F4+0.01 -> 0.24 | H4: =G4 -> 0.24 | I4: =H4 -> 0.24 | J4: =I4 -> 0.24 | K4: =J4+0.01 -> 0.25
A5: Target D&A as % of Revenue | B5: 0.13 | C5: 0.13 | D5: =C5-0.005 -> 0.125 | E5: =D5-0.005 -> 0.12 | F5: =E5 -> 0.12 | G5: =F5 -> 0.12 | H5: =G5-0.005 -> 0.115 | I5: =H5 -> 0.115 | J5: =I5-0.005 -> 0.11 | K5: =J5 -> 0.11
A6: Target Capex as % of Revenue | B6: =INDEX(Scenarios!D3:D5, MATCH($B$1, Scenarios!A3:A5, 0)) -> 0.13 | C6: =B6-0.005 -> 0.125 | D6: =C6-0.005 -> 0.12 | E6: =D6-0.005 -> 0.115 | F6: =E6-0.005 -> 0.11 | G6: =F6-0.005 -> 0.105 | H6: =G6-0.005 -> 0.1 | I6: =H6-0.005 -> 0.095 | J6: =I6-0.005 -> 0.09 | K6: =J6-0.005 -> 0.085
A7: Tax Rate | B7: 0.24 | C7: 0.24 | D7: 0.24 | E7: 0.24 | F7: 0.24 | G7: 0.24 | H7: 0.24 | I7: 0.24 | J7: 0.24 | K7: 0.24
A8: Change in net working capital as % of change in revenue | B8: 0.06 | C8: 0.06 | D8: 0.06 | E8: 0.06 | F8: 0.06 | G8: 0.06 | H8: 0.06 | I8: 0.06 | J8: 0.06 | K8: 0.06
A9: Capital Structure & Valuation Assumptions
A10: Risk-Free Rate | B10: 0.03
A11: Equity market Risk premium | B11: 0.05
A12: Beta for Infineon | B12: 1.3
A13: Cost of Equity | B13: =B10+B12*B11 -> 0.095
A14: Cost of Debt | B14: 0.04
A15: Debt Weight | B15: 0.25
A16: WACC | B16: =INDEX(Scenarios!E3:E5, MATCH($B$1, Scenarios!A3:A5, 0)) -> 0.07885
A17: Terminal Growth Rate | B17: =INDEX(Scenarios!F3:F5, MATCH($B$1, Scenarios!A3:A5, 0)) -> 0.025
A18: Net Cash or Net Debt | B18: ='Historical Fin'!G13 -> -4727
A19: Number of Shares (milions) | B19: 1306

Sheet Historical Fin
A2: Financial Data (In millions) | B2: 2020 | C2: 2021 | D2: 2022 | E2: 2023 | F2: 2024 | G2: 2025
A3: Total Revenue | B3: 8567 | C3: 11060 | D3: 14218 | E3: 16309 | F3: 14955 | G3: 14662
A4: Gross Profit | B4: 2776 | C4: 4260 | D4: 6131 | E4: 7413 | F4: 6069 | G4: 5753
A5: Operating Profit | B5: 581 | C5: 1470 | D5: 2845 | E5: 3948 | F5: 2190 | G5: 1515
A6: EBIT* | B6: 525 | C6: 1469 | D6: 2854 | E6: 4019 | F6: 2232 | G6: 1515
A7: EBITDA | B7: 1785 | C7: 982 | D7: 4518 | E7: 5773 | F7: 4097 | G7: =G6+1917 -> 3432
A8: Income Tax | B8: -52 | C8: -144 | D8: -537 | E8: -782 | F8: -378 | G8: -370
A9: Profit from Continuing Operations | B9: 372 | C9: 1175 | D9: 2186 | E9: 3139 | F9: 1780 | G9: 1005
A11: Total Assets | B11: 21999 | C11: 23334 | D11: 26912 | E11: 28439 | F11: 28639 | G11: 30470
A12: Total Equity | B12: 10219 | C12: 11401 | D12: 14944 | E12: 17044 | F12: 17219 | G12: 17051
A13: Net Cash Position | B13: -3806 | C13: -2663 | D13: -1945 | E13: -1143 | F13: -2610 | G13: -4727
A14: Financial Debt | B14: 7033 | C14: 6585 | D14: 5662 | E14: 4733 | F14: 4811 | G14: 6829
A15: Cash Flows from Operating Activities | B15: 1817 | C15: 3063 | D15: 3986 | E15: 3962 | F15: 3541 | G15: 3178
A16: Purchases of PPE and Intangibles (Capex) | B16: -1099 | C16: -1497 | D16: -2310 | E16: -2994 | F16: -2719 | G16: -2094
A17: Depreciation and Amortization | B17: 1260 | C17: 1513 | D17: 1664 | E17: 1754 | F17: 1865 | G17: 1917
A18: *(the historical figures before 2025 use the company‑defined EBIT)
A19: Revenue Growth | B19: - | C19: =C3/B3-1 -> 0.29100035 | D19: =D3/C3-1 -> 0.28553345 | E19: =E3/D3-1 -> 0.1470671 | F19: =F3/E3-1 -> -0.083021644 | G19: =G3/F3-1 -> -0.01959211
A20: EBITDA Margin | B20: =B7/B3 -> 0.20835765 | C20: =C7/C3 -> 0.088788427 | D20: =D7/D3 -> 0.31776621 | E20: =E7/E3 -> 0.35397633 | F20: =F7/F3 -> 0.2739552 | G20: =G7/G3 -> 0.23407448
A21: EBIT Margin | B21: =B6/B3 -> 0.061281662 | C21: =C6/C3 -> 0.13282098 | D21: =D6/D3 -> 0.20073147 | E21: =E6/E3 -> 0.24642835 | F21: =F6/F3 -> 0.14924774 | G21: =G6/G3 -> 0.10332833
A22: Effective Tax Rate | B22: =-B8/B6 -> 0.099047619 | C22: =-C8/C6 -> 0.098025868 | D22: =-D8/D6 -> 0.18815697 | E22: =-E8/E6 -> 0.19457577 | F22: =-F8/F6 -> 0.16935484 | G22: =-G8/G6 -> 0.24422442
A23: Capex as % of Revenue | B23: =-B16/B3 -> 0.12828295 | C23: =-C16/C3 -> 0.13535262 | D23: =-D16/D3 -> 0.16247011 | E23: =-E16/E3 -> 0.18357962 | F23: =-F16/F3 -> 0.1818121 | G23: =-G16/G3 -> 0.14281817
A24: D&A as % of Revenue | B24: =B17/B3 -> 0.14707599 | C24: =C17/C3 -> 0.13679928 | D24: =D17/D3 -> 0.11703474 | E24: =E17/E3 -> 0.10754798 | F24: =F17/F3 -> 0.12470746 | G24: =G17/G3 -> 0.13074615

Sheet Forecast 
A2: Forecast | B2: 2026 | C2: 2027 | D2: 2028 | E2: 2029 | F2: 2030 | G2: 2031 | H2: 2032 | I2: 2033 | J2: 2034 | K2: 2035
A3: Revenue | B3: ='Historical Fin'!G3*(1+Assumptions!B3) -> 15981.58 | C3: =B3*(1+Assumptions!C3) -> 17260.106 | D3: =C3*(1+Assumptions!D3) -> 18468.314 | E3: =D3*(1+Assumptions!E3) -> 19391.73 | F3: =E3*(1+Assumptions!F3) -> 19973.481 | G3: =F3*(1+Assumptions!G3) -> 20572.686 | H3: =G3*(1+Assumptions!H3) -> 21189.866 | I3: =H3*(1+Assumptions!I3) -> 21613.664 | J3: =I3*(1+Assumptions!J3) -> 22045.937 | K3: =J3*(1+Assumptions!K3) -> 22486.856
A4: EBITDA | B4: =B3*Assumptions!B4 -> 3356.1318 | C4: =C3*Assumptions!C4 -> 3797.2234 | D4: =D3*Assumptions!D4 -> 4247.7122 | E4: =E3*Assumptions!E4 -> 4460.0978 | F4: =F3*Assumptions!F4 -> 4593.9007 | G4: =G3*Assumptions!G4 -> 4937.4446 | H4: =H3*Assumptions!H4 -> 5085.5679 | I4: =I3*Assumptions!I4 -> 5187.2793 | ... K4: =K3*Assumptions!K4 -> 5621.7139
A5: D&A | B5: =B3*Assumptions!B5 -> 2077.6054 | C5: =C3*Assumptions!C5 -> 2243.8138 | D5: =D3*Assumptions!D5 -> 2308.5392 | E5: =E3*Assumptions!E5 -> 2327.0075 | F5: =F3*Assumptions!F5 -> 2396.8178 | G5: =G3*Assumptions!G5 -> 2468.7223 | H5: =H3*Assumptions!H5 -> 2436.8346 | I5: =I3*Assumptions!I5 -> 2485.5713 | ... K5: =K3*Assumptions!K5 -> 2473.5541
A6: EBITDA | B6: =B4-B5 -> 1278.5264 | C6: =C4-C5 -> 1553.4096 | D6: =D4-D5 -> 1939.173 | E6: =E4-E5 -> 2133.0902 | F6: =F4-F5 -> 2197.083 | G6: =G4-G5 -> 2468.7223 | H6: =H4-H5 -> 2648.7333 | I6: =I4-I5 -> 2701.708 | ... K6: =K4-K5 -> 3148.1598
A7: Taxes | B7: =-B6*Assumptions!B7 -> -306.84634 | C7: =-C6*Assumptions!C7 -> -372.8183 | D7: =-D6*Assumptions!D7 -> -465.40151 | E7: =-E6*Assumptions!E7 -> -511.94166 | F7: =-F6*Assumptions!F7 -> -527.29991 | G7: =-G6*Assumptions!G7 -> -592.49335 | H7: =-H6*Assumptions!H7 -> -635.69599 | I7: =-I6*Assumptions!I7 -> -648.40991 | ... K7: =-K6*Assumptions!K7 -> -755.55835
A8: NOPAT | B8: =B6-B7 -> 1585.3727 | C8: =C6-C7 -> 1926.2279 | D8: =D6-D7 -> 2404.5745 | E8: =E6-E7 -> 2645.0319 | F8: =F6-F7 -> 2724.3829 | G8: =G6-G7 -> 3061.2157 | H8: =H6-H7 -> 3284.4293 | I8: =I6-I7 -> 3350.1179 | ... K8: =K6-K7 -> 3903.7182
A9: Capex | B9: =-B3*Assumptions!B6 -> -2077.6054 | C9: =-C3*Assumptions!C6 -> -2157.5133 | D9: =-D3*Assumptions!D6 -> -2216.1977 | E9: =-E3*Assumptions!E6 -> -2230.0489 | F9: =-F3*Assumptions!F6 -> -2197.083 | G9: =-G3*Assumptions!G6 -> -2160.132 | H9: =-H3*Assumptions!H6 -> -2118.9866 | I9: =-I3*Assumptions!I6 -> -2053.2981 | ... K9: =-K3*Assumptions!K6 -> -1911.3827
A10: Change in Working Capital | B10: =-(B3-'Historical Fin'!G3)*Assumptions!B8 -> -79.1748 | C10: =-(C3-'Historical Fin'!H3)*Assumptions!C8 -> -1035.6064 | D10: =-(D3-'Historical Fin'!I3)*Assumptions!D8 -> -1108.0988 | E10: =-(E3-'Historical Fin'!J3)*Assumptions!E8 -> -1163.5038 | F10: =-(F3-'Historical Fin'!K3)*Assumptions!F8 -> -1198.4089 | G10: =-(G3-'Historical Fin'!L3)*Assumptions!G8 -> -1234.3612 | H10: =-(H3-'Historical Fin'!M3)*Assumptions!H8 -> -1271.392 | I10: =-(I3-'Historical Fin'!N3)*Assumptions!I8 -> -1296.8198 | ... K10: =-(K3-'Historical Fin'!P3)*Assumptions!K8 -> -1349.2113
A11: FCFF | B11: =B8+B5+B10+B9 -> 1506.1979 | C11: =C8+C5+C10+C9 -> 976.92202 | D11: =D8+D5+D10+D9 -> 1388.8172 | E11: =E8+E5+E10+E9 -> 1578.4868 | F11: =F8+F5+F10+F9 -> 1725.7088 | G11: =G8+G5+G10+G9 -> 2135.4448 | H11: =H8+H5+H10+H9 -> 2330.8853 | I11: =I8+I5+I10+I9 -> 2485.5713 | ... K11: =K8+K5+K10+K9 -> 3116.6782

Sheet DCF
A2: DCF | B2: 2026 | C2: 2027 | D2: 2028 | E2: 2029 | F2: 2030 | G2: 2031 | H2: 2032 | I2: 2033 | J2: 2034 | K2: 2035
A3: FCFF | B3: ='Forecast '!B11 -> 1506.1979 | C3: ='Forecast '!C11 -> 976.92202 | D3: ='Forecast '!D11 -> 1388.8172 | E3: ='Forecast '!E11 -> 1578.4868 | F3: ='Forecast '!F11 -> 1725.7088 | G3: ='Forecast '!G11 -> 2135.4448 | H3: ='Forecast '!H11 -> 2330.8853 | I3: ='Forecast '!I11 -> 2485.5713 | ... K3: ='Forecast '!K11 -> 3116.6782
A4: Discount Factots | B4: =1/(1+Assumptions!B16)^1 -> 0.92691292 | C4: =1/(1+Assumptions!B16)^2 -> 0.85916755 | D4: =1/(1+Assumptions!B16)^3 -> 0.7963735 | E4: =1/(1+Assumptions!B16)^4 -> 0.73816889 | F4: =1/(1+Assumptions!B16)^5 -> 0.68421828 | G4: =1/(1+Assumptions!B16)^6 -> 0.63421076 | H4: =1/(1+Assumptions!B16)^7 -> 0.58785814 | I4: =1/(1+Assumptions!B16)^8 -> 0.54489331 | J4: =1/(1+Assumptions!B16)^9 -> 0.50506864 | K4: =1/(1+Assumptions!B16)^10 -> 0.46815465
A5: Present Value of FCFF | B5: =B3*B4 -> 1396.1143 | C5: =C3*C4 -> 839.33971 | D5: =D3*D4 -> 1106.0172 | E5: =E3*E4 -> 1165.1898 | F5: =F3*F4 -> 1180.7615 | G5: =G3*G4 -> 1354.3221 | H5: =H3*H4 -> 1370.2299 | I5: =I3*I4 -> 1354.3712 | ... K5: =K3*K4 -> 1459.0874
A6: Terminal Value of FCFF | B6: - | C6: - | D6: - | E6: - | F6: - | G6: - | H6: - | I6: - | J6: - | K6: =K3/(Assumptions!B16-Assumptions!B17) -> 57877.033
A7: Present Value of Terminal Value | B7: - | C7: - | D7: - | E7: - | F7: - | G7: - | H7: - | I7: - | J7: - | K7: =K6*K4 -> 27095.402
A8: Entreprise Value | B8: - | C8: - | D8: - | E8: - | F8: - | G8: - | H8: - | I8: - | J8: - | K8: =SUM(B5:K5)+K7 -> 39670.362
A9: Equity Value | B9: - | C9: - | D9: - | E9: - | F9: - | G9: - | H9: - | I9: - | J9: - | K9: =K8-Assumptions!B18 -> 44397.362
A10: Implied price per share | B10: - | C10: - | D10: - | E10: - | F10: - | G10: - | H10: - | I10: - | J10: - | K10: =K9/Assumptions!B19 -> 33.994917
A11: Fair Value | B11: =$K$10*(1+Assumptions!B13)^1 -> 37.224435 | C11: =$K$10*(1+Assumptions!B13)^2 -> 40.760756 | D11: =$K$10*(1+Assumptions!B13)^3 -> 44.633028 | E11: =$K$10*(1+Assumptions!B13)^4 -> 48.873165 | F11: =$K$10*(1+Assumptions!B13)^5 -> 53.516116 | G11: =$K$10*(1+Assumptions!B13)^6 -> 58.600147 | H11: =$K$10*(1+Assumptions!B13)^7 -> 64.167161 | I11: =$K$10*(1+Assumptions!B13)^8 -> 70.263041 | J11: =$K$10*(1+Assumptions!B13)^9 -> 76.93803 | K11: =$K$10*(1+Assumptions!B13)^10 -> 84.247143

Sheet Sensitives
A2: Variants | B2: 0.07 | C2: 0.075 | D2: 0.07885 | E2: 0.085 | F2: 0.09 | G2: WACC
A3: 0.015 | B3: 36.03 | C3: 32.98 | D3: 30.96 | E3: 28.2 | F3: 26.31
A4: 0.02 | B4: 38.26 | C4: 34.75 | D4: 32.46 | E4: 29.37 | F4: 27.28
A5: 0.025 | B5: 40.98 | C5: 36.87 | D5: =DCF!K10 -> 33.994917 | E5: 30.74 | F5: 28.4
A6: 0.03 | B6: 44.39 | C6: 39.47 | D6: 36.38 | E6: 32.36 | F6: 29.7
A7: 0.035 | B7: 48.77 | C7: 42.72 | D7: 39.02 | E7: 34.29 | F7: 31.24
A8: Terminal Growth

Sheet Scenarios
A2: Scenario | B2: Revenue Growth | C2: EBITDA Margin | D2: Capex | E2: WACC | F2: Terminal Growth
A3: Base | B3: 0.09 | C3: 0.21 | D3: 0.13 | E3: 0.07885 | F3: 0.025
A4: Bull | B4: 0.11 | C4: 0.23 | D4: 0.12 | E4: 0.075 | F4: 0.03
A5: Bear | B5: 0.06 | C5: 0.19 | D5: 0.14 | E5: 0.085 | F5: 0.02

Sheet Thesis & Reccomendation
B1: Investment Thesis and Recommendation
B2: Infineon is a leading power and mixed‑signal semiconductor manufacturer exposed to structurally attractive themes such as electric vehicles, renewables and AI‑driven data centers, but its current share price embeds very optimistic expectations. Based on a 10‑year DCF, your base‑case intrinsic value is around €34–35 per share, well below the current market price (~€80–83), implying substantial downside and supporting a Sell / Overweight downside risk recommendation.
B3: DCF framework and base case
B4: I modeled a 10‑year explicit forecast (FY 2026–2035) using historical data from 2020–2025 and management disclosures. Revenue grows from €14.7bn in 2025 to about €22.5bn by 2035, implying a mid‑single‑digit CAGR in the outer years as growth fades from 9% in 2026 to 2% from 2033 onward. EBITDA margin expands from roughly 21% in 2026 to 25% in 2035, reflecting operating leverage, ongoing efficiency programs and some normalization of under‑utilization costs, while D&A and capex as a percentage of revenue gradually decline from low‑teens into high single digits as the current investment cycle matures.
B5: Free cash flow to the firm (FCFF) rises from about €1.5bn in 2026 to just over €3.1bn in 2035, after deducting capex and working‑capital investment equal to 6% of revenue growth each year. You discount FCFF at a WACC of 7.89%, derived from a 3% German 10‑year risk‑free rate, 5% equity risk premium, beta of 1.3, 9.5% cost of equity, 4% pre‑tax cost of debt, 25% target debt weight and a 24% tax rate; the terminal value uses a 2.5% perpetual growth rate consistent with long‑run nominal GDP and sector prospects. Summing the present value of explicit FCFF and the terminal value yields an enterprise value of roughly €40.8bn and, after adding net debt of about €4.7bn and dividing by 1,306m shares, an implied price per share of c.€34.9 in the base case.
B6: I also compute an “intrinsic value path” by rolling this €34.9 fair value forward at the 9.5% cost of equity, which gives indicative fair values of ~€38.2, €41.8, €45.8, €50.1 and €54.9 in 2026–2030 respectively if the stock were fairly priced today and investors earned their required return. Compared with a spot price around €80–83, the market is discounting much stronger growth and/or structurally higher margins than your conservative model assumes.
B7: Scenario Analysis
B8: My scenario work tests how coherent changes in operating assumptions translate into valuation.
B9: Base case (described above) produces a fair value of roughly €34–35 per share, with FCFF roughly doubling over the forecast period and terminal economics anchored by 25% EBITDA margin and 2.5% terminal growth.
B10: Bull case assumes stronger demand and better execution: higher revenue growth, more aggressive margin expansion, somewhat lower capex intensity and the same discount‑rate framework, leading to a much higher 2035 cash‑flow base. Under these assumptions, implied value reaches around €57 per share by 2035 in your DCF sheet, with near‑term “fair values” along the intrinsic path in the €60–130 range; this essentially reverses the call and suggests upside if Infineon can sustain very strong growth and profitability.
B11: Bear case reflects slower growth, pressure on margins and sustained capex and working‑capital needs, resulting in more subdued FCFF growth from sub‑€1bn in 2026 to about €1.7bn in 2035. Discounted at the same WACC and terminal growth framework, the Bear case yields implied “fair values” rising from roughly €19–20 in 2026 to around €43–44 by 2035, underlining substantial downside if macro and end‑market conditions disappoint.
B12: Taken together, the scenario range is wide, but under realistic Base and Bear assumptions the stock looks overvalued at current levels, while the Bull case requires optimistic assumptions about AI data‑center demand, EV penetration and sustained pricing power.
... B21: Catalysts to watch are quarterly earnings surprises (particularly on margins and free cash flow), updates on fab utilization and capex plans, and any sizeable M&A or policy changes affecting European semiconductor subsidies.
